internal_link_juicer_api_client/__init__.py
internal_link_juicer_api_client/ilj_api_client.py
internal_link_juicer_api_client-1.0.3.dist-info/LICENSE
internal_link_juicer_api_client-1.0.3.dist-info/METADATA
internal_link_juicer_api_client-1.0.3.dist-info/WHEEL
internal_link_juicer_api_client-1.0.3.dist-info/top_level.txt
internal_link_juicer_api_client-1.0.3.dist-info/RECORD
