Metadata-Version: 2.2
Name: internal_link_juicer_api_client
Version: 1.0.3
Summary: An Unofficial Python client for the Internal Link Juicer WordPress plugin API.
Home-page: https://github.com/onur222/internal-link-juicer-api-client
Author: Onur Gürpınar
Author-email: onurgurpinar@gmail.com
Project-URL: Bug Reports, https://github.com/onur222/internal-link-juicer-api-client/issues
Project-URL: Source, https://github.com/onur222/internal-link-juicer-api-client
Classifier: Development Status :: 3 - Alpha
Classifier: Intended Audience :: Developers
Classifier: License :: OSI Approved :: MIT License
Classifier: Programming Language :: Python :: 3
Classifier: Programming Language :: Python :: 3.7
Classifier: Programming Language :: Python :: 3.8
Classifier: Programming Language :: Python :: 3.9
Classifier: Programming Language :: Python :: 3.10
Classifier: Programming Language :: Python :: 3.11
Classifier: Programming Language :: Python :: 3.12
Requires-Python: >=3.7
License-File: LICENSE
Requires-Dist: requests
Requires-Dist: phpserialize
Dynamic: author
Dynamic: author-email
Dynamic: classifier
Dynamic: description
Dynamic: description-content-type
Dynamic: home-page
Dynamic: project-url
Dynamic: requires-dist
Dynamic: requires-python
Dynamic: summary
